NanoMethCluster/BAMReadAnalyzer.py
NanoMethCluster/DataAnalyzer.py
NanoMethCluster/KmerDataProcessor.py
NanoMethCluster/PlotGenerator.py
NanoMethCluster/__init__.py
NanoMethCluster/cli.py
nanomethcluster-0.1.1.dist-info/METADATA
nanomethcluster-0.1.1.dist-info/WHEEL
nanomethcluster-0.1.1.dist-info/entry_points.txt
nanomethcluster-0.1.1.dist-info/licenses/LICENSE
nanomethcluster-0.1.1.dist-info/RECORD
