Metadata-Version: 2.3
Name: NanoMethCluster
Version: 0.1.1
Summary: A package for analyzing nanopore sequencing data, focusing on clustering raw reads based on methylation and k-mers.
Project-URL: Homepage, https://github.com/alekseizarubin/NanoMethCluster
Author-email: Zarubin Aleksei <a.a.zarubin@gmail.com>
License-Expression: MIT
License-File: LICENSE
